pointer_brakes/__init__.py
pointer_brakes/_sim.py
pointer_brakes/_vec2d.py
pointer_brakes/exceptions.py
pointer_brakes/py.typed
pointer_brakes-0.2.1.dist-info/METADATA
pointer_brakes-0.2.1.dist-info/WHEEL
pointer_brakes-0.2.1.dist-info/licenses/LICENSE
pointer_brakes-0.2.1.dist-info/RECORD
