Metadata-Version: 2.3
Name: pointer-brakes
Version: 0.2.1
Summary: A mouse pointer simulation driven by touch input. The pointer slowly brakes to a stop.
Project-URL: Documentation, https://github.com/ChrisArgyle/pointer-brakes#readme
Project-URL: Issues, https://github.com/ChrisArgyle/pointer-brakes/issues
Project-URL: Source, https://github.com/ChrisArgyle/pointer-brakes
Author-email: ChrisArgyle <chrisisdiy@gmail.com>
License-Expression: MIT
License-File: LICENSE
Classifier: Development Status :: 4 - Beta
Classifier: Programming Language :: Python
Classifier: Programming Language :: Python :: 3.8
Classifier: Programming Language :: Python :: 3.9
Classifier: Programming Language :: Python :: 3.10
Classifier: Programming Language :: Python :: 3.11
Classifier: Programming Language :: Python :: 3.12
Classifier: Programming Language :: Python :: Implementation :: CPython
Classifier: Programming Language :: Python :: Implementation :: PyPy
Requires-Python: >=3.8
